nlweb_azure_models/__init__.py
nlweb_azure_models/embedding/azure_oai_embedding.py
nlweb_azure_models/llm/azure_oai.py
nlweb_azure_models-0.5.6.dist-info/METADATA
nlweb_azure_models-0.5.6.dist-info/WHEEL
nlweb_azure_models-0.5.6.dist-info/top_level.txt
nlweb_azure_models-0.5.6.dist-info/RECORD
